ThorsonWiki-0.1a10.dist-info/DESCRIPTION.rst
ThorsonWiki-0.1a10.dist-info/METADATA
ThorsonWiki-0.1a10.dist-info/RECORD
ThorsonWiki-0.1a10.dist-info/WHEEL
ThorsonWiki-0.1a10.dist-info/metadata.json
ThorsonWiki-0.1a10.dist-info/top_level.txt
thorson_wiki/__init__.py
thorson_wiki/admin.py
thorson_wiki/apps.py
thorson_wiki/forms.py
thorson_wiki/markup.py
thorson_wiki/models.py
thorson_wiki/orderedtoc.py
thorson_wiki/search_indexes.py
thorson_wiki/search_sites.py
thorson_wiki/secrets.py
thorson_wiki/signals.py
thorson_wiki/tests.py
thorson_wiki/thorsonwikilink.py
thorson_wiki/urls.py
thorson_wiki/views.py
thorson_wiki/migrations/0001_initial.py
thorson_wiki/migrations/0002_auto_20170106_0131.py
thorson_wiki/migrations/__init__.py
thorson_wiki/static/thorson_wiki/css/article.css
thorson_wiki/static/thorson_wiki/css/base.css
thorson_wiki/static/thorson_wiki/css/bootstrap-theme.css
thorson_wiki/static/thorson_wiki/css/bootstrap-theme.css.map
thorson_wiki/static/thorson_wiki/css/bootstrap-theme.min.css
thorson_wiki/static/thorson_wiki/css/bootstrap-theme.min.css.map
thorson_wiki/static/thorson_wiki/css/bootstrap.css
thorson_wiki/static/thorson_wiki/css/bootstrap.css.map
thorson_wiki/static/thorson_wiki/css/bootstrap.min.css
thorson_wiki/static/thorson_wiki/css/bootstrap.min.css.map
thorson_wiki/static/thorson_wiki/fonts/glyphicons-halflings-regular.eot
thorson_wiki/static/thorson_wiki/fonts/glyphicons-halflings-regular.svg
thorson_wiki/static/thorson_wiki/fonts/glyphicons-halflings-regular.ttf
thorson_wiki/static/thorson_wiki/fonts/glyphicons-halflings-regular.woff
thorson_wiki/static/thorson_wiki/fonts/glyphicons-halflings-regular.woff2
thorson_wiki/static/thorson_wiki/js/bootstrap.js
thorson_wiki/static/thorson_wiki/js/bootstrap.min.js
thorson_wiki/static/thorson_wiki/js/jquery.min.js
thorson_wiki/static/thorson_wiki/js/npm.js
thorson_wiki/templates/search/indexes/thorson_wiki/article_text.txt
thorson_wiki/templates/thorson_wiki/_check_field.html
thorson_wiki/templates/thorson_wiki/_nav.html
thorson_wiki/templates/thorson_wiki/_text_field.html
thorson_wiki/templates/thorson_wiki/_update_form.html
thorson_wiki/templates/thorson_wiki/_user_form.html
