Metadata-Version: 2.0
Name: ThorsonWiki
Version: 0.1a10
Summary: Simple, modular wiki sites with Django
Home-page: https://github.com/thorsonlinguistics/thorson_wiki
Author: Jacob Collard
Author-email: jacob@thorsonlinguistics.com
License: MIT
Platform: UNKNOWN
Classifier: Development Status :: 3 - Alpha
Classifier: Environment :: Web Environment
Classifier: Framework :: Django :: 1.10
Classifier: License :: OSI Approved :: MIT License
Classifier: Programming Language :: Python :: 2
Classifier: Programming Language :: Python :: 3
Requires-Dist: bleach
Requires-Dist: Django
Requires-Dist: django-widget-tweaks
Requires-Dist: Markdown
